deeplive/__init__.py
deeplive/app.py
deeplive/capturer.py
deeplive/cluster_analysis.py
deeplive/core.py
deeplive/face_analyser.py
deeplive/gettext.py
deeplive/globals.py
deeplive/metadata.py
deeplive/predicter.py
deeplive/test_face_swap.py
deeplive/typing.py
deeplive/ui.py
deeplive/utilities.py
deeplive/video_capture.py
deeplive/processors/__init__.py
deeplive/processors/frame/__init__.py
deeplive/processors/frame/core.py
deeplive/processors/frame/face_enhancer.py
deeplive/processors/frame/face_swapper.py
deeplive/ui/__init__.py
deeplive/ui/constants.py
deeplive/ui/main_window.py
deeplive/ui/mapper_window.py
deeplive/ui/preview_window.py
deeplive/ui/utils.py
deeplive/ui/webcam_window.py
deeplive-0.1.0.dist-info/licenses/LICENSE
deeplive-0.1.0.dist-info/METADATA
deeplive-0.1.0.dist-info/WHEEL
deeplive-0.1.0.dist-info/entry_points.txt
deeplive-0.1.0.dist-info/top_level.txt
deeplive-0.1.0.dist-info/RECORD
